dolfin_mech/Constraint.py
dolfin_mech/Expression_MeshFunction_cpp.py
dolfin_mech/FOI.py
dolfin_mech/Kinematics.py
dolfin_mech/Kinematics_Inverse.py
dolfin_mech/Kinematics_Linearized.py
dolfin_mech/Loading.py
dolfin_mech/Material.py
dolfin_mech/Material_Elastic.py
dolfin_mech/Material_Elastic_ExponentialNeoHookean.py
dolfin_mech/Material_Elastic_ExponentialOgdenCiarletGeymonat.py
dolfin_mech/Material_Elastic_Hooke.py
dolfin_mech/Material_Elastic_Kirchhoff.py
dolfin_mech/Material_Elastic_Lung_Wbulk.py
dolfin_mech/Material_Elastic_Lung_Wpore.py
dolfin_mech/Material_Elastic_Lung_Wskel.py
dolfin_mech/Material_Elastic_MooneyRivlin.py
dolfin_mech/Material_Elastic_NeoHookean.py
dolfin_mech/Material_Elastic_NeoHookeanMooneyRivlin.py
dolfin_mech/Material_Elastic_OgdenCiarletGeymonat.py
dolfin_mech/Material_Elastic_OgdenCiarletGeymonatNeoHookean.py
dolfin_mech/Material_Elastic_OgdenCiarletGeymonatNeoHookeanMooneyRivlin.py
dolfin_mech/Material_Elastic_Porous.py
dolfin_mech/Material_Inelastic.py
dolfin_mech/NonlinearSolver.py
dolfin_mech/Operator.py
dolfin_mech/Operator_Constraint_MacroscopicStressComponent.py
dolfin_mech/Operator_HyperElasticity.py
dolfin_mech/Operator_HyperHydrostaticPressure.py
dolfin_mech/Operator_HyperIncompressibility.py
dolfin_mech/Operator_Inertia.py
dolfin_mech/Operator_LinearizedElasticity.py
dolfin_mech/Operator_LinearizedHydrostaticPressure.py
dolfin_mech/Operator_LinearizedIncompressibility.py
dolfin_mech/Operator_Loading_PressureBalancingGravity.py
dolfin_mech/Operator_Loading_SurfaceForce.py
dolfin_mech/Operator_Loading_SurfacePressure.py
dolfin_mech/Operator_Loading_SurfacePressureGradient.py
dolfin_mech/Operator_Loading_SurfaceTension.py
dolfin_mech/Operator_Loading_VolumeForce.py
dolfin_mech/Operator_MicroPoro_DeformedFluidVolume.py
dolfin_mech/Operator_MicroPoro_DeformedSolidVolume.py
dolfin_mech/Operator_MicroPoro_DeformedSurfaceArea.py
dolfin_mech/Operator_MicroPoro_DeformedTotalVolume.py
dolfin_mech-2025.12.5.dist-info/licenses/LICENSE
dolfin_mech-2025.12.5.dist-info/METADATA
dolfin_mech-2025.12.5.dist-info/WHEEL
dolfin_mech-2025.12.5.dist-info/top_level.txt
dolfin_mech-2025.12.5.dist-info/RECORD
