Metadata-Version: 2.4
Name: dolfin_mech
Version: 2025.12.5
Summary: [![PyPi Version](https://img.shields.io/pypi/v/dolfin-mech.svg?style=flat-square)](https://pypi.org/project/dolfin-mech)
Home-page: https://github.com/mgenet/dolfin_mech
Author: Martin Genet
Author-email: martin.genet@polytechnique.edu
License: GPLv3
Classifier: Programming Language :: Python :: 3
Classifier: License :: OSI Approved :: GNU General Public License v3 (GPLv3)
Classifier: Operating System :: OS Independent
License-File: LICENSE
Requires-Dist: gmsh~=4.9
Requires-Dist: matplotlib~=3.5
Requires-Dist: meshio~=5.3
Requires-Dist: numpy~=1.23
Requires-Dist: pandas~=1.3
Requires-Dist: vtk~=9.2
Requires-Dist: myPythonLibrary
Requires-Dist: myVTKPythonLibrary
Requires-Dist: vtkpython_cbl
Dynamic: author
Dynamic: author-email
Dynamic: classifier
Dynamic: description
Dynamic: description-content-type
Dynamic: home-page
Dynamic: license
Dynamic: license-file
Dynamic: requires-dist
Dynamic: summary
